{
    "model": "page",
    "presets": [
        {
            "label": "Empty page",
            "thumbnail": "images/page-empty.png",
            "data": {
                "title": "Empty page"
            }
        },
        {
            "label": "Landing",
            "thumbnail": "images/page-landing.png",
            "data": {
                "title": "Example landing page",
                "sections": [
                    {
                        "type": "hero",
                        "heading": "This is your main value proposition",
                        "body": "And a super compelling supporting paragraph that makes the user immediately want to click the button below.\n",
                        "image": {
                            "src": "/src/content/pages/_images/corgi-hero.jpg",
                            "alt": "Corgi"
                        },
                        "button": {
                            "label": "Get Started",
                            "url": "/"
                        },
                        "layout": "imgRight",
                        "background": "primary"
                    },
                    {
                        "type": "quote",
                        "quote": "Netlify is just amazing. Fast, reliable, good community, perfect to publish web projects from Github without any headache.",
                        "authorName": "Author Name",
                        "authorTitle": "Author title",
                        "authorImage": {
                            "src": "/src/content/pages/_images/corgi-author.jpg",
                            "alt": "Author Corgi"
                        },
                        "background": "light"
                    }
                ]
            }
        }
    ]
}
