{
  "$schema": "https://ui.shadcn.com/schema/registry-item.json",
  "name": "footer-1",
  "type": "registry:block",
  "registryDependencies": [
    "section",
    "channel",
    "logo",
    "social"
  ],
  "files": [
    {
      "path": "src/blocks/footer-1.tsx",
      "content": "import type { BlockProps } from \"@/lib/types\"\nimport { Channel } from \"@/components/ui/channel\"\nimport { Logo, LogoImage } from \"@/components/ui/logo\"\nimport { Section, SectionContainer } from \"@/components/ui/section\"\nimport { Social } from \"@/components/ui/social\"\n\nexport default function ({\n  logo,\n  description,\n  links,\n  socials,\n  channels,\n  menus,\n  name,\n  hours,\n}: BlockProps) {\n  return (\n    <Section className=\"py-0\">\n      <SectionContainer className=\"flex flex-col\">\n        <div className=\"grid w-full grid-cols-[repeat(auto-fit,minmax(30px,1fr))] justify-between gap-16 border-t py-16\">\n          <div className=\"col-span-3 flex max-w-xs flex-col\">\n            {logo && (\n              <Logo href=\"/\">\n                {logo?.src && <LogoImage {...logo} />}\n                {logo?.title && logo.title}\n              </Logo>\n            )}\n            {description && (\n              <p className=\"text-muted-foreground text-sm not-first:mt-3\">\n                {description}\n              </p>\n            )}\n            {channels && channels.length > 0 && (\n              <div className=\"-ml-2.5 flex flex-col items-start not-first:mt-4\">\n                {channels.map((channel, i) => (\n                  <Channel variant=\"ghost\" key={i} {...channel} />\n                ))}\n              </div>\n            )}\n            <div className=\"mt-6 flex gap-4\">\n              {socials?.map((social, i) => (\n                <Social\n                  className=\"text-muted-foreground hover:text-foreground !size-auto\"\n                  key={i}\n                  variant=\"link\"\n                  href={social}\n                />\n              ))}\n            </div>\n          </div>\n          {hours && (\n            <div className=\"text-muted-foreground col-span-3 flex basis-[192px] flex-col gap-2 text-sm\">\n              <h4 className=\"text-foreground text-sm font-semibold\">\n                Drukke tijden\n              </h4>\n              <img src=\"/images/busy.webp\" alt=\"Drukke tijden\" />\n            </div>\n          )}\n          {hours && (\n            <div className=\"text-muted-foreground col-span-2 flex basis-[192px] flex-col gap-2 text-sm\">\n              <h4 className=\"text-foreground text-sm font-semibold\">\n                {hours.title}\n              </h4>\n              <p className=\"text-muted-foreground mb-2 text-xs\">\n                {hours.description}\n              </p>\n              <p className=\"flex justify-between\">\n                <span>ma.</span> {hours.ma}\n              </p>\n              <p className=\"flex justify-between\">\n                <span>di.</span> {hours.di}\n              </p>\n              <p className=\"flex justify-between\">\n                <span>wo.</span> {hours.wo}\n              </p>\n              <p className=\"flex justify-between\">\n                <span>do.</span> {hours.do}\n              </p>\n              <p className=\"flex justify-between\">\n                <span>vr.</span> {hours.vr}\n              </p>\n              <p className=\"flex justify-between\">\n                <span>za.</span> {hours.za}\n              </p>\n              <p className=\"flex justify-between\">\n                <span>zo.</span> {hours.zo}\n              </p>\n            </div>\n          )}\n          {menus?.map((menu, i) => (\n            <div className=\"menu flex flex-col items-start gap-4\" key={i}>\n              <h4 className=\"text-foreground text-sm font-semibold\">\n                {menu.text}\n              </h4>\n              <menu className=\"flex w-full flex-col items-start gap-3\">\n                {menu.links?.map(({ href, text }) => (\n                  <a\n                    className=\"text-muted-foreground hover:text-foreground text-sm font-normal transition-colors\"\n                    key={href}\n                    href={href}\n                  >\n                    {text}\n                  </a>\n                ))}\n              </menu>\n            </div>\n          ))}\n        </div>\n        <div className=\"flex flex-col flex-wrap items-start justify-between gap-x-6 gap-y-4 border-t py-6 md:flex-row md:items-center\">\n          {name && (\n            <p className=\"text-muted-foreground mr-auto text-xs\">\n              © {new Date().getFullYear()} {name}\n            </p>\n          )}\n          <div className=\"flex flex-wrap items-center gap-x-4 gap-y-1\">\n            {links?.map(({ text, href }, i) => (\n              <a\n                className=\"text-muted-foreground hover:text-foreground text-xs transition-colors\"\n                key={i}\n                href={href}\n              >\n                {text}\n              </a>\n            ))}\n          </div>\n        </div>\n      </SectionContainer>\n    </Section>\n  )\n}\n",
      "type": "registry:block"
    }
  ]
}